{
  "main": {
    "id": "6680fff01f9c7f93",
    "type": "split",
    "children": [
      {
        "id": "93562f4b3844e7a0",
        "type": "tabs",
        "children": [
          {
            "id": "bd54c547efb1eb53",
            "type": "leaf",
            "state": {
              "type": "markdown",
              "state": {
                "file": "airlines/RJ.md",
                "mode": "source",
                "source": false
              },
              "icon": "lucide-file",
              "title": "RJ"
            }
          }
        ]
      }
    ],
    "direction": "vertical"
  },
  "left": {
    "id": "58632eadea1a0280",
    "type": "split",
    "children": [
      {
        "id": "115180c7818647ef",
        "type": "tabs",
        "children": [
          {
            "id": "1a42cd1662754338",
            "type": "leaf",
            "state": {
              "type": "file-explorer",
              "state": {
                "sortOrder": "alphabetical",
                "autoReveal": false
              },
              "icon": "lucide-folder-closed",
              "title": "Files"
            }
          },
          {
            "id": "bdd7ff9531a16b43",
            "type": "leaf",
            "state": {
              "type": "search",
              "state": {
                "query": "",
                "matchingCase": false,
                "explainSearch": false,
                "collapseAll": false,
                "extraContext": false,
                "sortOrder": "alphabetical"
              },
              "icon": "lucide-search",
              "title": "Search"
            }
          },
          {
            "id": "a4448ee896900947",
            "type": "leaf",
            "state": {
              "type": "bookmarks",
              "state": {},
              "icon": "lucide-bookmark",
              "title": "Bookmarks"
            }
          }
        ]
      }
    ],
    "direction": "horizontal",
    "width": 300
  },
  "right": {
    "id": "b72e0e4220faa029",
    "type": "split",
    "children": [
      {
        "id": "6d59a04c2f2013ba",
        "type": "tabs",
        "children": [
          {
            "id": "ec876c5d560a2d1a",
            "type": "leaf",
            "state": {
              "type": "backlink",
              "state": {
                "file": "methods/Worldspan LH-LS-LX Pricing.md",
                "collapseAll": false,
                "extraContext": false,
                "sortOrder": "alphabetical",
                "showSearch": false,
                "searchQuery": "",
                "backlinkCollapsed": false,
                "unlinkedCollapsed": true
              },
              "icon": "links-coming-in",
              "title": "Backlinks for Worldspan LH-LS-LX Pricing"
            }
          },
          {
            "id": "65d8b4d29a8c47f0",
            "type": "leaf",
            "state": {
              "type": "outgoing-link",
              "state": {
                "file": "methods/Worldspan LH-LS-LX Pricing.md",
                "linksCollapsed": false,
                "unlinkedCollapsed": true
              },
              "icon": "links-going-out",
              "title": "Outgoing links from Worldspan LH-LS-LX Pricing"
            }
          },
          {
            "id": "2d37cb420194dd91",
            "type": "leaf",
            "state": {
              "type": "tag",
              "state": {
                "sortOrder": "frequency",
                "useHierarchy": true,
                "showSearch": false,
                "searchQuery": ""
              },
              "icon": "lucide-tags",
              "title": "Tags"
            }
          },
          {
            "id": "03f66918a149135e",
            "type": "leaf",
            "state": {
              "type": "outline",
              "state": {
                "followCursor": false,
                "showSearch": false,
                "searchQuery": ""
              },
              "icon": "lucide-list",
              "title": "Outline"
            }
          },
          {
            "id": "e4e2502b47d18fee",
            "type": "leaf",
            "state": {
              "type": "copilot-chat-view",
              "state": {},
              "icon": "message-square",
              "title": "Copilot"
            }
          },
          {
            "id": "c262c1260a2e8f02",
            "type": "leaf",
            "state": {
              "type": "git-view",
              "state": {},
              "icon": "lucide-file",
              "title": "Plugin no longer active"
            }
          }
        ],
        "currentTab": 4
      }
    ],
    "direction": "horizontal",
    "width": 423.5
  },
  "left-ribbon": {
    "hiddenItems": {
      "switcher:Open quick switcher": false,
      "graph:Open graph view": false,
      "canvas:Create new canvas": false,
      "daily-notes:Open today's daily note": false,
      "templates:Insert template": false,
      "command-palette:Open command palette": false,
      "copilot:Open Copilot Chat": false,
      "obsidian-git:Open Git source control": false
    }
  },
  "active": "bd54c547efb1eb53",
  "lastOpenFiles": [
    "airlines/VS.md",
    "airlines/UA.md",
    "airlines/TK.md",
    "airlines/SV.md",
    "airlines/RJ.md",
    "airlines/QR.md",
    "airlines/OS.md",
    "airlines/MS.md",
    "airlines/ME.md",
    "airlines/LX.md",
    "airlines/LH.md",
    "airlines/KL.md",
    "airlines/IB.md",
    "airlines/HU.md",
    "airlines/FZ.md",
    "airlines/F9-NK-SY.md",
    "airlines/EY.md",
    "airlines/ET.md",
    "airlines/EK.md",
    "airlines/DL.md",
    "airlines/B6.md",
    "airlines/AZ.md",
    "airlines/AT.md",
    "airlines/AS.md",
    "airlines/AL.md",
    "airlines/AF.md",
    "airlines/Untitled",
    "gds/worldspan",
    "gds/sabre",
    "gds/amadeus",
    "gds",
    "utils/nvim/lua/plugins/nvim-tree.lua~",
    "utils/nvim/lua/plugins/oil.lua~",
    "utils/alacritty/alacritty.toml~",
    "utils/nvim/lazy-lock.json",
    "utils/alacritty/alacritty.toml"
  ]
}